<?xml version="1.0" encoding="utf-8" ?>
<hibernate-mapping xmlns="urn:nhibernate-mapping-2.2" assembly="QLSV.Core" namespace="QLSV.Core.Domain">
  <class name="QLSV.Core.Domain.Kythi, QLSV.Core" table="Kythi">
    <id name="ID" column="ID" type="Int32" unsaved-value="0">
      <generator class="identity" />
    </id>
    <property name="MaKyThi" column="MaKyThi"  type="string" length="255" />
    <property name="TenKyThi" column="TenKyThi"  type="string" length="255" />
    <property name="NgayThi" column="NgayThi"  type="string" length="50" />
    <property name="ThoiGianLamBai" column="ThoiGianLamBai"  type="int" />
    <property name="ThoiGianBatDau" column="ThoiGianBatDau"  type="string" length="255" />
    <property name="ThoiGianKetThuc" column="ThoiGianKetThuc"  type="string" length="255" />
  </class>
</hibernate-mapping>
