<?xml version="1.0" encoding="utf-8" ?>
<hibernate-mapping xmlns="urn:nhibernate-mapping-2.2" assembly="QLSV.Core" namespace="QLSV.Core.Domain">
  <class name="QLSV.Core.Domain.PhongThi, QLSV.Core" table="PhongThi">
    <id name="ID" column="ID" type="Int32" unsaved-value="0">
      <generator class="identity" />
    </id>
    <property name="TenPhong" column="TenPhong"  type="string" length="255" />
    <property name="SucChua" column="SucChua"  type="int"/>
    <property name="GhiChu" column="GhiChu"  type="string" length="255"/>
  </class>
</hibernate-mapping>